[
  {
    "id": "98ef9035-27e1-44da-b86b-a5fac4e3f924",
    "name": "Wayne Deckow Sr.",
    "phone": "1-637-576-5984 x163",
    "email": "Carmela51@hotmail.com",
    "job": "Product Group Orchestrator"
  },
  {
    "id": "c0c8cdf5-3484-4d58-bf5b-f37cc0670fb2",
    "name": "Alicia Schiller",
    "phone": "600.225.1601",
    "email": "Althea51@gmail.com",
    "job": "Central Usability Engineer"
  },
  {
    "id": "14145bcf-7007-495b-9392-889df56865f7",
    "name": "Leon Wolf",
    "phone": "528-455-1736 x3067",
    "email": "Jane46@yahoo.com",
    "job": "Corporate Branding Analyst"
  },
  {
    "id": "c2b96b2b-09dd-47ed-925d-5baf37eecf8b",
    "name": "Regina Terry",
    "phone": "(837) 676-6789",
    "email": "Virginie_Grady64@gmail.com",
    "job": "International Web Supervisor"
  },
  {
    "id": "59e222eb-c265-4090-bdc9-83e0179c7162",
    "name": "Clara Fahey",
    "phone": "678.601.9256",
    "email": "Alexane4@yahoo.com",
    "job": "Central Functionality Strategist"
  },
  {
    "id": "edba790d-e165-49d6-b7e5-5eab3e770176",
    "name": "Stuart Greenfelder",
    "phone": "374.951.2202 x74581",
    "email": "Arlene_Greenholt38@hotmail.com",
    "job": "Central Factors Executive"
  },
  {
    "id": "983d8c54-c967-4eb7-a918-0268b917c322",
    "name": "Viola Hamill",
    "phone": "(367) 662-4649 x76567",
    "email": "Duane23@hotmail.com",
    "job": "Principal Identity Technician"
  }
]